{
  "_format": "hh-sol-cache-2",
  "files": {
    "E:\\Projects\\pancakeswap-fork\\africunia-swap\\pancake-swap-core\\contracts\\PancakePair.sol": {
      "lastModificationDate": 1661518424826,
      "contentHash": "30a9b1e3f7b2fd1de16d44c40fcb0100",
      "sourceName": "contracts/PancakePair.sol",
      "solcConfig": {
        "version": "0.5.16",
        "settings": {
          "optimizer": {
            "enabled": false,
            "runs": 200
          },
          "outputSelection": {
            "*": {
              "*": [
                "abi",
                "evm.bytecode",
                "evm.deployedBytecode",
                "evm.methodIdentifiers",
                "metadata"
              ],
              "": [
                "ast"
              ]
            }
          }
        }
      },
      "imports": [
        "./interfaces/IPancakePair.sol",
        "./PancakeERC20.sol",
        "./libraries/Math.sol",
        "./libraries/UQ112x112.sol",
        "./interfaces/IERC20.sol",
        "./interfaces/IPancakeFactory.sol",
        "./interfaces/IPancakeCallee.sol"
      ],
      "versionPragmas": [
        "=0.5.16"
      ],
      "artifacts": [
        "PancakePair"
      ]
    },
    "E:\\Projects\\pancakeswap-fork\\africunia-swap\\pancake-swap-core\\contracts\\PancakeERC20.sol": {
      "lastModificationDate": 1661518424825,
      "contentHash": "2747a36217843195259c4a5b73e692bb",
      "sourceName": "contracts/PancakeERC20.sol",
      "solcConfig": {
        "version": "0.5.16",
        "settings": {
          "optimizer": {
            "enabled": false,
            "runs": 200
          },
          "outputSelection": {
            "*": {
              "*": [
                "abi",
                "evm.bytecode",
                "evm.deployedBytecode",
                "evm.methodIdentifiers",
                "metadata"
              ],
              "": [
                "ast"
              ]
            }
          }
        }
      },
      "imports": [
        "./interfaces/IPancakeERC20.sol",
        "./libraries/SafeMath.sol"
      ],
      "versionPragmas": [
        "=0.5.16"
      ],
      "artifacts": [
        "PancakeERC20"
      ]
    },
    "E:\\Projects\\pancakeswap-fork\\africunia-swap\\pancake-swap-core\\contracts\\libraries\\Math.sol": {
      "lastModificationDate": 1661518424830,
      "contentHash": "bee6c1959728d5d42c14151076cebd83",
      "sourceName": "contracts/libraries/Math.sol",
      "solcConfig": {
        "version": "0.5.16",
        "settings": {
          "optimizer": {
            "enabled": false,
            "runs": 200
          },
          "outputSelection": {
            "*": {
              "*": [
                "abi",
                "evm.bytecode",
                "evm.deployedBytecode",
                "evm.methodIdentifiers",
                "metadata"
              ],
              "": [
                "ast"
              ]
            }
          }
        }
      },
      "imports": [],
      "versionPragmas": [
        "=0.5.16"
      ],
      "artifacts": [
        "Math"
      ]
    },
    "E:\\Projects\\pancakeswap-fork\\africunia-swap\\pancake-swap-core\\contracts\\libraries\\UQ112x112.sol": {
      "lastModificationDate": 1661518424830,
      "contentHash": "2a703244e9f645c6fb297a983ce7c9c4",
      "sourceName": "contracts/libraries/UQ112x112.sol",
      "solcConfig": {
        "version": "0.5.16",
        "settings": {
          "optimizer": {
            "enabled": false,
            "runs": 200
          },
          "outputSelection": {
            "*": {
              "*": [
                "abi",
                "evm.bytecode",
                "evm.deployedBytecode",
                "evm.methodIdentifiers",
                "metadata"
              ],
              "": [
                "ast"
              ]
            }
          }
        }
      },
      "imports": [],
      "versionPragmas": [
        "=0.5.16"
      ],
      "artifacts": [
        "UQ112x112"
      ]
    },
    "E:\\Projects\\pancakeswap-fork\\africunia-swap\\pancake-swap-core\\contracts\\libraries\\SafeMath.sol": {
      "lastModificationDate": 1661518424830,
      "contentHash": "a65356c329efeffba75210664f5df3cd",
      "sourceName": "contracts/libraries/SafeMath.sol",
      "solcConfig": {
        "version": "0.5.16",
        "settings": {
          "optimizer": {
            "enabled": false,
            "runs": 200
          },
          "outputSelection": {
            "*": {
              "*": [
                "abi",
                "evm.bytecode",
                "evm.deployedBytecode",
                "evm.methodIdentifiers",
                "metadata"
              ],
              "": [
                "ast"
              ]
            }
          }
        }
      },
      "imports": [],
      "versionPragmas": [
        "=0.5.16"
      ],
      "artifacts": [
        "SafeMath"
      ]
    },
    "E:\\Projects\\pancakeswap-fork\\africunia-swap\\pancake-swap-core\\contracts\\PancakeFactory.sol": {
      "lastModificationDate": 1661518424825,
      "contentHash": "1a278eb235ccd670b0060fc65a913fae",
      "sourceName": "contracts/PancakeFactory.sol",
      "solcConfig": {
        "version": "0.5.16",
        "settings": {
          "optimizer": {
            "enabled": false,
            "runs": 200
          },
          "outputSelection": {
            "*": {
              "*": [
                "abi",
                "evm.bytecode",
                "evm.deployedBytecode",
                "evm.methodIdentifiers",
                "metadata"
              ],
              "": [
                "ast"
              ]
            }
          }
        }
      },
      "imports": [
        "./interfaces/IPancakeFactory.sol",
        "./PancakePair.sol"
      ],
      "versionPragmas": [
        "=0.5.16"
      ],
      "artifacts": [
        "PancakeFactory"
      ]
    },
    "E:\\Projects\\pancakeswap-fork\\africunia-swap\\pancake-swap-core\\contracts\\test\\ERC20.sol": {
      "lastModificationDate": 1661518424831,
      "contentHash": "28b13ee59f8440e280b1a54f221a43ce",
      "sourceName": "contracts/test/ERC20.sol",
      "solcConfig": {
        "version": "0.5.16",
        "settings": {
          "optimizer": {
            "enabled": false,
            "runs": 200
          },
          "outputSelection": {
            "*": {
              "*": [
                "abi",
                "evm.bytecode",
                "evm.deployedBytecode",
                "evm.methodIdentifiers",
                "metadata"
              ],
              "": [
                "ast"
              ]
            }
          }
        }
      },
      "imports": [
        "../PancakeERC20.sol"
      ],
      "versionPragmas": [
        "=0.5.16"
      ],
      "artifacts": [
        "ERC20"
      ]
    },
    "E:\\Projects\\pancakeswap-fork\\africunia-swap\\pancake-swap-core\\contracts\\ClaimBackCake.sol": {
      "lastModificationDate": 1661518424823,
      "contentHash": "a312629fee60305f7c59746eb2fdf230",
      "sourceName": "contracts/ClaimBackCake.sol",
      "solcConfig": {
        "version": "0.6.12",
        "settings": {
          "optimizer": {
            "enabled": false,
            "runs": 200
          },
          "outputSelection": {
            "*": {
              "*": [
                "abi",
                "evm.bytecode",
                "evm.deployedBytecode",
                "evm.methodIdentifiers",
                "metadata"
              ],
              "": [
                "ast"
              ]
            }
          }
        }
      },
      "imports": [],
      "versionPragmas": [
        ">=0.6.0 <0.8.0",
        ">=0.6.0 <0.8.0",
        ">=0.4.0",
        ">=0.6.0 <0.8.0",
        ">=0.6.2 <0.8.0",
        ">=0.6.0 <0.8.0",
        ">=0.6.0 <0.8.0",
        ">=0.6.0 <0.8.0",
        ">=0.6.0 <0.8.0",
        ">=0.6.2 <0.8.0",
        ">=0.6.0 <0.8.0",
        ">=0.6.0 <0.8.0",
        "^0.6.0",
        "^0.6.0",
        "^0.6.12",
        "^0.6.12"
      ],
      "artifacts": [
        "AccessControl",
        "Address",
        "AnniversaryAchievement",
        "ClaimBackCake",
        "Context",
        "Counters",
        "ERC721Holder",
        "EnumerableSet",
        "IBEP20",
        "IERC165",
        "IERC721",
        "IERC721Receiver",
        "Ownable",
        "PancakeProfile",
        "SafeBEP20",
        "SafeMath"
      ]
    },
    "E:\\Projects\\pancakeswap-fork\\africunia-swap\\pancake-swap-core\\contracts\\MasterChef.sol": {
      "lastModificationDate": 1661518424824,
      "contentHash": "8d7dcfe98e37b138b27bdf07845a8d01",
      "sourceName": "contracts/MasterChef.sol",
      "solcConfig": {
        "version": "0.6.12",
        "settings": {
          "optimizer": {
            "enabled": false,
            "runs": 200
          },
          "outputSelection": {
            "*": {
              "*": [
                "abi",
                "evm.bytecode",
                "evm.deployedBytecode",
                "evm.methodIdentifiers",
                "metadata"
              ],
              "": [
                "ast"
              ]
            }
          }
        }
      },
      "imports": [],
      "versionPragmas": [
        "0.6.12"
      ],
      "artifacts": [
        "Address",
        "BEP20",
        "CakeToken",
        "Context",
        "IBEP20",
        "IMigratorChef",
        "MasterChef",
        "Ownable",
        "SafeBEP20",
        "SafeMath",
        "SyrupBar"
      ]
    },
    "E:\\Projects\\pancakeswap-fork\\africunia-swap\\pancake-swap-core\\contracts\\Migration.sol": {
      "lastModificationDate": 1661518424824,
      "contentHash": "6f3dc9936ec2cff1666c76993e7d6531",
      "sourceName": "contracts/Migration.sol",
      "solcConfig": {
        "version": "0.6.12",
        "settings": {
          "optimizer": {
            "enabled": false,
            "runs": 200
          },
          "outputSelection": {
            "*": {
              "*": [
                "abi",
                "evm.bytecode",
                "evm.deployedBytecode",
                "evm.methodIdentifiers",
                "metadata"
              ],
              "": [
                "ast"
              ]
            }
          }
        }
      },
      "imports": [],
      "versionPragmas": [
        ">=0.4.25 <0.7.0"
      ],
      "artifacts": [
        "Migrations"
      ]
    },
    "E:\\Projects\\pancakeswap-fork\\africunia-swap\\pancake-swap-core\\contracts\\SousChef.sol": {
      "lastModificationDate": 1661518424826,
      "contentHash": "5b04ced9cb2a684f0d4be6f28f989cc4",
      "sourceName": "contracts/SousChef.sol",
      "solcConfig": {
        "version": "0.6.12",
        "settings": {
          "optimizer": {
            "enabled": false,
            "runs": 200
          },
          "outputSelection": {
            "*": {
              "*": [
                "abi",
                "evm.bytecode",
                "evm.deployedBytecode",
                "evm.methodIdentifiers",
                "metadata"
              ],
              "": [
                "ast"
              ]
            }
          }
        }
      },
      "imports": [],
      "versionPragmas": [
        "0.6.12"
      ],
      "artifacts": [
        "Address",
        "IBEP20",
        "SafeBEP20",
        "SafeMath",
        "SousChef"
      ]
    },
    "E:\\Projects\\pancakeswap-fork\\africunia-swap\\pancake-swap-core\\contracts\\interfaces\\IERC20.sol": {
      "lastModificationDate": 1661518424827,
      "contentHash": "3d2b948a9266ee66b6e739de97c7e6e9",
      "sourceName": "contracts/interfaces/IERC20.sol",
      "solcConfig": {
        "version": "0.8.4",
        "settings": {
          "optimizer": {
            "enabled": false,
            "runs": 200
          },
          "outputSelection": {
            "*": {
              "*": [
                "abi",
                "evm.bytecode",
                "evm.deployedBytecode",
                "evm.methodIdentifiers",
                "metadata"
              ],
              "": [
                "ast"
              ]
            }
          }
        }
      },
      "imports": [],
      "versionPragmas": [
        ">=0.5.0"
      ],
      "artifacts": [
        "IERC20"
      ]
    },
    "E:\\Projects\\pancakeswap-fork\\africunia-swap\\pancake-swap-core\\contracts\\interfaces\\IPancakeCallee.sol": {
      "lastModificationDate": 1661518424827,
      "contentHash": "d110e8ea54e84297d7a980b1a218f5ce",
      "sourceName": "contracts/interfaces/IPancakeCallee.sol",
      "solcConfig": {
        "version": "0.8.4",
        "settings": {
          "optimizer": {
            "enabled": false,
            "runs": 200
          },
          "outputSelection": {
            "*": {
              "*": [
                "abi",
                "evm.bytecode",
                "evm.deployedBytecode",
                "evm.methodIdentifiers",
                "metadata"
              ],
              "": [
                "ast"
              ]
            }
          }
        }
      },
      "imports": [],
      "versionPragmas": [
        ">=0.5.0"
      ],
      "artifacts": [
        "IPancakeCallee"
      ]
    },
    "E:\\Projects\\pancakeswap-fork\\africunia-swap\\pancake-swap-core\\contracts\\interfaces\\IPancakeFactory.sol": {
      "lastModificationDate": 1661518424829,
      "contentHash": "21a09f1df5792450572a8a1a8da5fa7d",
      "sourceName": "contracts/interfaces/IPancakeFactory.sol",
      "solcConfig": {
        "version": "0.8.4",
        "settings": {
          "optimizer": {
            "enabled": false,
            "runs": 200
          },
          "outputSelection": {
            "*": {
              "*": [
                "abi",
                "evm.bytecode",
                "evm.deployedBytecode",
                "evm.methodIdentifiers",
                "metadata"
              ],
              "": [
                "ast"
              ]
            }
          }
        }
      },
      "imports": [],
      "versionPragmas": [
        ">=0.5.0"
      ],
      "artifacts": [
        "IPancakeFactory"
      ]
    },
    "E:\\Projects\\pancakeswap-fork\\africunia-swap\\pancake-swap-core\\contracts\\interfaces\\IPancakeERC20.sol": {
      "lastModificationDate": 1661518424828,
      "contentHash": "cffdf5dbe4b564dbdf64fa62968083b5",
      "sourceName": "contracts/interfaces/IPancakeERC20.sol",
      "solcConfig": {
        "version": "0.8.4",
        "settings": {
          "optimizer": {
            "enabled": false,
            "runs": 200
          },
          "outputSelection": {
            "*": {
              "*": [
                "abi",
                "evm.bytecode",
                "evm.deployedBytecode",
                "evm.methodIdentifiers",
                "metadata"
              ],
              "": [
                "ast"
              ]
            }
          }
        }
      },
      "imports": [],
      "versionPragmas": [
        ">=0.5.0"
      ],
      "artifacts": [
        "IPancakeERC20"
      ]
    },
    "E:\\Projects\\pancakeswap-fork\\africunia-swap\\pancake-swap-core\\contracts\\interfaces\\IPancakePair.sol": {
      "lastModificationDate": 1662127040242,
      "contentHash": "831ea5848a0260afc9863bf4e3dd0989",
      "sourceName": "contracts/interfaces/IPancakePair.sol",
      "solcConfig": {
        "version": "0.8.4",
        "settings": {
          "optimizer": {
            "enabled": false,
            "runs": 200
          },
          "outputSelection": {
            "*": {
              "*": [
                "abi",
                "evm.bytecode",
                "evm.deployedBytecode",
                "evm.methodIdentifiers",
                "metadata"
              ],
              "": [
                "ast"
              ]
            }
          }
        }
      },
      "imports": [],
      "versionPragmas": [
        ">=0.5.0"
      ],
      "artifacts": [
        "IPancakePair"
      ]
    },
    "E:\\Projects\\pancakeswap-fork\\africunia-swap\\pancake-swap-core\\contracts\\uniswap\\interfaces\\IERC20.sol": {
      "lastModificationDate": 1662126643577,
      "contentHash": "2290ca2ec74690ed9024d986955ef431",
      "sourceName": "contracts/uniswap/interfaces/IERC20.sol",
      "solcConfig": {
        "version": "0.8.4",
        "settings": {
          "optimizer": {
            "enabled": false,
            "runs": 200
          },
          "outputSelection": {
            "*": {
              "*": [
                "abi",
                "evm.bytecode",
                "evm.deployedBytecode",
                "evm.methodIdentifiers",
                "metadata"
              ],
              "": [
                "ast"
              ]
            }
          }
        }
      },
      "imports": [],
      "versionPragmas": [
        ">=0.5.0"
      ],
      "artifacts": [
        "IERC20"
      ]
    },
    "E:\\Projects\\pancakeswap-fork\\africunia-swap\\pancake-swap-core\\contracts\\uniswap\\interfaces\\IUniswapV2Callee.sol": {
      "lastModificationDate": 1662126643577,
      "contentHash": "dee30d5845c0662c462da74fbe109539",
      "sourceName": "contracts/uniswap/interfaces/IUniswapV2Callee.sol",
      "solcConfig": {
        "version": "0.8.4",
        "settings": {
          "optimizer": {
            "enabled": false,
            "runs": 200
          },
          "outputSelection": {
            "*": {
              "*": [
                "abi",
                "evm.bytecode",
                "evm.deployedBytecode",
                "evm.methodIdentifiers",
                "metadata"
              ],
              "": [
                "ast"
              ]
            }
          }
        }
      },
      "imports": [],
      "versionPragmas": [
        ">=0.5.0"
      ],
      "artifacts": [
        "IUniswapV2Callee"
      ]
    },
    "E:\\Projects\\pancakeswap-fork\\africunia-swap\\pancake-swap-core\\contracts\\uniswap\\interfaces\\IUniswapV2Factory.sol": {
      "lastModificationDate": 1662126643578,
      "contentHash": "51d78f670a7cb6d7aa4d8096f82a99c6",
      "sourceName": "contracts/uniswap/interfaces/IUniswapV2Factory.sol",
      "solcConfig": {
        "version": "0.8.4",
        "settings": {
          "optimizer": {
            "enabled": false,
            "runs": 200
          },
          "outputSelection": {
            "*": {
              "*": [
                "abi",
                "evm.bytecode",
                "evm.deployedBytecode",
                "evm.methodIdentifiers",
                "metadata"
              ],
              "": [
                "ast"
              ]
            }
          }
        }
      },
      "imports": [],
      "versionPragmas": [
        ">=0.5.0"
      ],
      "artifacts": [
        "IUniswapV2Factory"
      ]
    },
    "E:\\Projects\\pancakeswap-fork\\africunia-swap\\pancake-swap-core\\contracts\\uniswap\\interfaces\\IUniswapV2ERC20.sol": {
      "lastModificationDate": 1662126643578,
      "contentHash": "605345701334b98242fd4108573ae444",
      "sourceName": "contracts/uniswap/interfaces/IUniswapV2ERC20.sol",
      "solcConfig": {
        "version": "0.8.4",
        "settings": {
          "optimizer": {
            "enabled": false,
            "runs": 200
          },
          "outputSelection": {
            "*": {
              "*": [
                "abi",
                "evm.bytecode",
                "evm.deployedBytecode",
                "evm.methodIdentifiers",
                "metadata"
              ],
              "": [
                "ast"
              ]
            }
          }
        }
      },
      "imports": [],
      "versionPragmas": [
        ">=0.5.0"
      ],
      "artifacts": [
        "IUniswapV2ERC20"
      ]
    },
    "E:\\Projects\\pancakeswap-fork\\africunia-swap\\pancake-swap-core\\contracts\\uniswap\\interfaces\\IUniswapV2Pair.sol": {
      "lastModificationDate": 1662126643578,
      "contentHash": "d021d78f40daea7a0f06e1d2eed0e968",
      "sourceName": "contracts/uniswap/interfaces/IUniswapV2Pair.sol",
      "solcConfig": {
        "version": "0.8.4",
        "settings": {
          "optimizer": {
            "enabled": false,
            "runs": 200
          },
          "outputSelection": {
            "*": {
              "*": [
                "abi",
                "evm.bytecode",
                "evm.deployedBytecode",
                "evm.methodIdentifiers",
                "metadata"
              ],
              "": [
                "ast"
              ]
            }
          }
        }
      },
      "imports": [],
      "versionPragmas": [
        ">=0.5.0"
      ],
      "artifacts": [
        "IUniswapV2Pair"
      ]
    },
    "E:\\Projects\\pancakeswap-fork\\africunia-swap\\pancake-swap-core\\contracts\\uniswap\\UniswapV2Pair.sol": {
      "lastModificationDate": 1662127274513,
      "contentHash": "4c035b0dd75977a04987556c1438c220",
      "sourceName": "contracts/uniswap/UniswapV2Pair.sol",
      "solcConfig": {
        "version": "0.5.16",
        "settings": {
          "optimizer": {
            "enabled": false,
            "runs": 200
          },
          "outputSelection": {
            "*": {
              "*": [
                "abi",
                "evm.bytecode",
                "evm.deployedBytecode",
                "evm.methodIdentifiers",
                "metadata"
              ],
              "": [
                "ast"
              ]
            }
          }
        }
      },
      "imports": [
        "./interfaces/IUniswapV2Pair.sol",
        "./UniswapV2ERC20.sol",
        "./libraries/Math.sol",
        "./libraries/UQ112x112.sol",
        "./interfaces/IERC20.sol",
        "./interfaces/IUniswapV2Factory.sol",
        "./interfaces/IUniswapV2Callee.sol"
      ],
      "versionPragmas": [
        "=0.5.16"
      ],
      "artifacts": [
        "UniswapV2Pair"
      ]
    },
    "E:\\Projects\\pancakeswap-fork\\africunia-swap\\pancake-swap-core\\contracts\\uniswap\\UniswapV2ERC20.sol": {
      "lastModificationDate": 1662126643575,
      "contentHash": "91a2001b4697613fd016ad98df162eff",
      "sourceName": "contracts/uniswap/UniswapV2ERC20.sol",
      "solcConfig": {
        "version": "0.5.16",
        "settings": {
          "optimizer": {
            "enabled": false,
            "runs": 200
          },
          "outputSelection": {
            "*": {
              "*": [
                "abi",
                "evm.bytecode",
                "evm.deployedBytecode",
                "evm.methodIdentifiers",
                "metadata"
              ],
              "": [
                "ast"
              ]
            }
          }
        }
      },
      "imports": [
        "./interfaces/IUniswapV2ERC20.sol",
        "./libraries/SafeMath.sol"
      ],
      "versionPragmas": [
        "=0.5.16"
      ],
      "artifacts": [
        "UniswapV2ERC20"
      ]
    },
    "E:\\Projects\\pancakeswap-fork\\africunia-swap\\pancake-swap-core\\contracts\\uniswap\\libraries\\Math.sol": {
      "lastModificationDate": 1662126643579,
      "contentHash": "807b5a3ee256f814ef1aeb0996fd9a85",
      "sourceName": "contracts/uniswap/libraries/Math.sol",
      "solcConfig": {
        "version": "0.5.16",
        "settings": {
          "optimizer": {
            "enabled": false,
            "runs": 200
          },
          "outputSelection": {
            "*": {
              "*": [
                "abi",
                "evm.bytecode",
                "evm.deployedBytecode",
                "evm.methodIdentifiers",
                "metadata"
              ],
              "": [
                "ast"
              ]
            }
          }
        }
      },
      "imports": [],
      "versionPragmas": [
        "=0.5.16"
      ],
      "artifacts": [
        "Math"
      ]
    },
    "E:\\Projects\\pancakeswap-fork\\africunia-swap\\pancake-swap-core\\contracts\\uniswap\\libraries\\UQ112x112.sol": {
      "lastModificationDate": 1662126643579,
      "contentHash": "b4c8a4d6e325bff8a4002ae0681eb036",
      "sourceName": "contracts/uniswap/libraries/UQ112x112.sol",
      "solcConfig": {
        "version": "0.5.16",
        "settings": {
          "optimizer": {
            "enabled": false,
            "runs": 200
          },
          "outputSelection": {
            "*": {
              "*": [
                "abi",
                "evm.bytecode",
                "evm.deployedBytecode",
                "evm.methodIdentifiers",
                "metadata"
              ],
              "": [
                "ast"
              ]
            }
          }
        }
      },
      "imports": [],
      "versionPragmas": [
        "=0.5.16"
      ],
      "artifacts": [
        "UQ112x112"
      ]
    },
    "E:\\Projects\\pancakeswap-fork\\africunia-swap\\pancake-swap-core\\contracts\\uniswap\\libraries\\SafeMath.sol": {
      "lastModificationDate": 1662126643579,
      "contentHash": "acf692d86aa69bcd2fe982bd93189262",
      "sourceName": "contracts/uniswap/libraries/SafeMath.sol",
      "solcConfig": {
        "version": "0.5.16",
        "settings": {
          "optimizer": {
            "enabled": false,
            "runs": 200
          },
          "outputSelection": {
            "*": {
              "*": [
                "abi",
                "evm.bytecode",
                "evm.deployedBytecode",
                "evm.methodIdentifiers",
                "metadata"
              ],
              "": [
                "ast"
              ]
            }
          }
        }
      },
      "imports": [],
      "versionPragmas": [
        "=0.5.16"
      ],
      "artifacts": [
        "SafeMath"
      ]
    },
    "E:\\Projects\\pancakeswap-fork\\africunia-swap\\pancake-swap-core\\contracts\\uniswap\\UniswapV2Factory.sol": {
      "lastModificationDate": 1662126643575,
      "contentHash": "d11e6f227d62998403ec093773bfa291",
      "sourceName": "contracts/uniswap/UniswapV2Factory.sol",
      "solcConfig": {
        "version": "0.5.16",
        "settings": {
          "optimizer": {
            "enabled": false,
            "runs": 200
          },
          "outputSelection": {
            "*": {
              "*": [
                "abi",
                "evm.bytecode",
                "evm.deployedBytecode",
                "evm.methodIdentifiers",
                "metadata"
              ],
              "": [
                "ast"
              ]
            }
          }
        }
      },
      "imports": [
        "./interfaces/IUniswapV2Factory.sol",
        "./UniswapV2Pair.sol"
      ],
      "versionPragmas": [
        "=0.5.16"
      ],
      "artifacts": [
        "UniswapV2Factory"
      ]
    },
    "E:\\Projects\\pancakeswap-fork\\africunia-swap\\pancake-swap-core\\contracts\\uniswap\\test\\ERC20.sol": {
      "lastModificationDate": 1662126643580,
      "contentHash": "5da3646d8bb418f39a51cc5b61c8b988",
      "sourceName": "contracts/uniswap/test/ERC20.sol",
      "solcConfig": {
        "version": "0.5.16",
        "settings": {
          "optimizer": {
            "enabled": false,
            "runs": 200
          },
          "outputSelection": {
            "*": {
              "*": [
                "abi",
                "evm.bytecode",
                "evm.deployedBytecode",
                "evm.methodIdentifiers",
                "metadata"
              ],
              "": [
                "ast"
              ]
            }
          }
        }
      },
      "imports": [
        "../UniswapV2ERC20.sol"
      ],
      "versionPragmas": [
        "=0.5.16"
      ],
      "artifacts": [
        "ERC20"
      ]
    }
  }
}
